{
  "Name": "DragonForce - Ashes Of The Dust",
  "Parts": [
    {
      "Time Signature": [
        4,
        4
      ],
      "Type": "Regular",
      "Part": [
        [
          [
            "Bass",
            [
              1,
              8
            ]
          ],
          [
            "HiHat",
            [
              1,
              8
            ],
            [
              "Loose"
            ]
          ]
        ],
        [
          [
            "HiHat",
            [
              1,
              8
            ]
          ]
        ],
        [
          [
            "Snare",
            [
              1,
              8
            ],
            [
              "CrossStick"
            ]
          ],
          [
            "HiHat",
            [
              1,
              8
            ]
          ]
        ],
        [
          [
            "HiHat",
            [
              1,
              8
            ],
            [
              "Open"
            ]
          ]
        ],
        [
          [
            "Rest",
            [
              1,
              16
            ]
          ]
        ],
        [
          [
            "HighTom",
            [
              1,
              16
            ],
            [
              "Flam"
            ]
          ]
        ],
        [
          [
            "HighTom",
            [
              1,
              16
            ],
            [
              "Drag"
            ]
          ]
        ],
        [
          [
            "Rest",
            [
              1,
              16
            ]
          ]
        ],
        [
          [
            "HighTom",
            [
              1,
              16
            ],
            [
              "Flam"
            ]
          ]
        ],
        [
          [
            "Rest",
            [
              1,
              16
            ]
          ]
        ],
        [
          [
            "Rest",
            [
              1,
              16
            ]
          ]
        ],
        [
          [
            "HighTom",
            [
              1,
              16
            ],
            [
              "Drag"
            ]
          ]
        ],
        [
          [
            "Rest",
            [
              1,
              1
            ]
          ]
        ],
        [
          [
            "Rest",
            [
              1,
              2
            ]
          ]
        ],
        [
          [
            "Snare",
            [
              1,
              2
            ]
          ],
          [
            "Bass",
            [
              1,
              2
            ]
          ]
        ],
        [
          [
            "HiHat",
            [
              1,
              8
            ],
            [
              "Open"
            ]
          ]
        ],
        [
          [
            "HiHat",
            [
              1,
              8
            ],
            [
              "Loose"
            ]
          ]
        ],
        [
          [
            "HiHat",
            [
              1,
              8
            ],
            [
              "Close"
            ]
          ]
        ],
        [
          [
            "HiHat",
            [
              1,
              8
            ],
            [
              "OpenClose"
            ]
          ]
        ],
        [
          [
            "HiHat",
            [
              1,
              8
            ],
            [
              "Accent"
            ]
          ]
        ],
        [
          [
            "HiHat",
            [
              1,
              8
            ],
            [
              "Ghost"
            ]
          ],
          [
            "Snare",
            [
              1,
              8
            ],
            [
              "Rimshot"
            ]
          ]
        ],
        [
          [
            "Snare",
            [
              1,
              8
            ],
            [
              "Right"
            ]
          ]
        ],
        [
          [
            "Snare",
            [
              1,
              8
            ],
            [
              "Left"
            ]
          ]
        ]
      ]
    }
  ]
}